graphene_sqlalchemy/__init__.py
graphene_sqlalchemy/converter.py
graphene_sqlalchemy/enums.py
graphene_sqlalchemy/fields.py
graphene_sqlalchemy/registry.py
graphene_sqlalchemy/types.py
graphene_sqlalchemy/utils.py
graphene_sqlalchemy/tests/__init__.py
graphene_sqlalchemy/tests/conftest.py
graphene_sqlalchemy/tests/models.py
graphene_sqlalchemy/tests/test_converter.py
graphene_sqlalchemy/tests/test_enums.py
graphene_sqlalchemy/tests/test_fields.py
graphene_sqlalchemy/tests/test_query.py
graphene_sqlalchemy/tests/test_query_enums.py
graphene_sqlalchemy/tests/test_reflected.py
graphene_sqlalchemy/tests/test_registry.py
graphene_sqlalchemy/tests/test_sort_enums.py
graphene_sqlalchemy/tests/test_types.py
graphene_sqlalchemy/tests/test_utils.py
graphene_sqlalchemy-2.2.2.dist-info/LICENSE.md
graphene_sqlalchemy-2.2.2.dist-info/METADATA
graphene_sqlalchemy-2.2.2.dist-info/WHEEL
graphene_sqlalchemy-2.2.2.dist-info/top_level.txt
graphene_sqlalchemy-2.2.2.dist-info/RECORD
