Metadata-Version: 2.1
Name: graphene-sqlalchemy
Version: 2.2.2
Summary: Graphene SQLAlchemy integration
Home-page: https://github.com/graphql-python/graphene-sqlalchemy
Author: Syrus Akbary
Author-email: me@syrusakbary.com
License: MIT
Keywords: api graphql protocol rest relay graphene
Platform: UNKNOWN
Classifier: Development Status :: 3 - Alpha
Classifier: Intended Audience :: Developers
Classifier: Topic :: Software Development :: Libraries
Classifier: Programming Language :: Python :: 2
Classifier: Programming Language :: Python :: 2.7
Classifier: Programming Language :: Python :: 3
Classifier: Programming Language :: Python :: 3.3
Classifier: Programming Language :: Python :: 3.4
Classifier: Programming Language :: Python :: 3.5
Classifier: Programming Language :: Python :: 3.6
Classifier: Programming Language :: Python :: 3.7
Classifier: Programming Language :: Python :: Implementation :: PyPy
Provides-Extra: dev
Provides-Extra: test
